{
  "calendar_version": "2.0",
  "generated_date": "2026-02-24",
  "site": "digitalshieldpro.com",
  "notes": "15 new articles targeting high-volume cybersecurity keywords with strong affiliate conversion potential. Avoids duplicating any of the 22 existing articles.",
  "affiliate_programs": {
    "nordvpn": "https://go.nordvpn.net/aff_c?offer_id=612&aff_id=141337&url_id=14830",
    "nordpass": "https://go.nordvpn.net/aff_c?offer_id=488&aff_id=141337",
    "kaspersky": "https://www.awin1.com/awclick.php?mid=19487&id=2776410",
    "bitdefender": "https://www.awin1.com/awclick.php?mid=11660&id=2776410",
    "eset": "https://www.awin1.com/awclick.php?mid=18785&id=2776410",
    "surfshark": "https://www.awin1.com/awclick.php?mid=36608&id=2776410"
  },
  "articles": [
    {
      "slug": "best-vpn-for-windows-pc-2026",
      "title": "Best VPN for Windows PC in 2026: Top 7 Tested and Ranked",
      "description": "A dedicated Windows VPN guide targeting the massive Windows user base. Covers native app quality, kill switch reliability on Windows, WireGuard/NordLynx performance on Windows 11, split tunneling features, and gaming latency. This addresses the most searched VPN platform query that the site currently lacks.",
      "category": "vpn",
      "content_type": "best-of-list",
      "target_keywords": [
        "best VPN for Windows",
        "best VPN for PC",
        "best VPN for Windows 11",
        "VPN for Windows 2026",
        "Windows VPN app",
        "best VPN for laptop"
      ],
      "affiliate_links": [
        {
          "product": "NordVPN",
          "url": "https://go.nordvpn.net/aff_c?offer_id=612&aff_id=141337&url_id=14830",
          "placement": "top-pick"
        },
        {
          "product": "Surfshark",
          "url": "https://www.awin1.com/awclick.php?mid=36608&id=2776410",
          "placement": "budget-pick"
        }
      ],
      "word_count_target": 3500,
      "priority": 1
    },
    {
      "slug": "best-antivirus-for-windows-11-2026",
      "title": "Best Antivirus for Windows 11 in 2026: Beyond Windows Defender",
      "description": "Targets the huge search volume around Windows 11 antivirus needs. Compares third-party solutions against the built-in Microsoft Defender, with independent lab test scores, real-world detection rates, and system performance impact benchmarks. Strong purchase intent keyword with direct path to affiliate conversion.",
      "category": "antivirus",
      "content_type": "best-of-list",
      "target_keywords": [
        "best antivirus for Windows 11",
        "best antivirus Windows 2026",
        "do I need antivirus Windows 11",
        "Windows Defender vs antivirus",
        "best antivirus for PC 2026",
        "antivirus for Windows 11"
      ],
      "affiliate_links": [
        {
          "product": "Bitdefender",
          "url": "https://www.awin1.com/awclick.php?mid=11660&id=2776410",
          "placement": "top-pick"
        },
        {
          "product": "Kaspersky",
          "url": "https://www.awin1.com/awclick.php?mid=19487&id=2776410",
          "placement": "runner-up"
        },
        {
          "product": "ESET",
          "url": "https://www.awin1.com/awclick.php?mid=18785&id=2776410",
          "placement": "advanced-users"
        },
        {
          "product": "Surfshark Antivirus",
          "url": "https://www.awin1.com/awclick.php?mid=36608&id=2776410",
          "placement": "budget-pick"
        }
      ],
      "word_count_target": 4000,
      "priority": 1
    },
    {
      "slug": "nordvpn-vs-surfshark-2026",
      "title": "NordVPN vs Surfshark 2026: Which VPN Is Actually Better?",
      "description": "Head-to-head comparison of the site's two primary VPN affiliates. This is a high-volume comparison query since both are top-5 VPN providers. Covers speed benchmarks, server networks, simultaneous connections, pricing tiers, streaming unblocking, and privacy policies. Every click leads to an affiliate conversion opportunity.",
      "category": "vpn",
      "content_type": "comparison",
      "target_keywords": [
        "NordVPN vs Surfshark",
        "Surfshark vs NordVPN",
        "NordVPN or Surfshark",
        "NordVPN vs Surfshark 2026",
        "NordVPN vs Surfshark comparison",
        "NordVPN vs Surfshark Reddit"
      ],
      "affiliate_links": [
        {
          "product": "NordVPN",
          "url": "https://go.nordvpn.net/aff_c?offer_id=612&aff_id=141337&url_id=14830",
          "placement": "overall-winner"
        },
        {
          "product": "Surfshark",
          "url": "https://www.awin1.com/awclick.php?mid=36608&id=2776410",
          "placement": "value-winner"
        }
      ],
      "word_count_target": 3500,
      "priority": 1
    },
    {
      "slug": "best-internet-security-suite-2026",
      "title": "Best Internet Security Suites in 2026: All-in-One Protection Compared",
      "description": "Targets users searching for comprehensive security bundles (antivirus + VPN + password manager + identity monitoring). These all-in-one suites have the highest average order values, making them extremely profitable for affiliates. Compares Bitdefender Premium Security, Norton 360, Kaspersky Premium, and ESET Home Security Ultimate.",
      "category": "antivirus",
      "content_type": "best-of-list",
      "target_keywords": [
        "best internet security suite 2026",
        "best security suite",
        "all in one security software",
        "best total security software",
        "internet security comparison",
        "complete security suite"
      ],
      "affiliate_links": [
        {
          "product": "Bitdefender",
          "url": "https://www.awin1.com/awclick.php?mid=11660&id=2776410",
          "placement": "top-pick"
        },
        {
          "product": "Kaspersky",
          "url": "https://www.awin1.com/awclick.php?mid=19487&id=2776410",
          "placement": "runner-up"
        },
        {
          "product": "ESET",
          "url": "https://www.awin1.com/awclick.php?mid=18785&id=2776410",
          "placement": "advanced-pick"
        },
        {
          "product": "NordVPN",
          "url": "https://go.nordvpn.net/aff_c?offer_id=612&aff_id=141337&url_id=14830",
          "placement": "best-vpn-addon"
        },
        {
          "product": "NordPass",
          "url": "https://go.nordvpn.net/aff_c?offer_id=488&aff_id=141337",
          "placement": "best-password-addon"
        }
      ],
      "word_count_target": 4500,
      "priority": 1
    },
    {
      "slug": "eset-review-2026",
      "title": "ESET Review 2026: Lightweight Antivirus for Power Users",
      "description": "Standalone review for ESET, one of the site's AWIN affiliate partners that lacks a dedicated review. ESET has a loyal following among tech-savvy users and consistent high marks from AV-TEST. Covers ESET NOD32, ESET Internet Security, and ESET Home Security tiers with real-world performance data.",
      "category": "antivirus",
      "content_type": "product-review",
      "target_keywords": [
        "ESET review 2026",
        "ESET NOD32 review",
        "ESET antivirus review",
        "is ESET good",
        "ESET Home Security review",
        "ESET vs Bitdefender"
      ],
      "affiliate_links": [
        {
          "product": "ESET",
          "url": "https://www.awin1.com/awclick.php?mid=18785&id=2776410",
          "placement": "primary-cta"
        },
        {
          "product": "Bitdefender",
          "url": "https://www.awin1.com/awclick.php?mid=11660&id=2776410",
          "placement": "alternative-recommendation"
        }
      ],
      "word_count_target": 3500,
      "priority": 1
    },
    {
      "slug": "how-to-protect-yourself-online-2026",
      "title": "How to Protect Yourself Online: The Complete Digital Security Checklist",
      "description": "Evergreen pillar page targeting broad informational queries about online safety. Functions as a hub linking to multiple product-focused articles. Covers VPN usage, antivirus protection, password management, 2FA, safe browsing, social media privacy, and email security. High traffic potential with multiple natural affiliate insertion points throughout the guide.",
      "category": "privacy",
      "content_type": "how-to-guide",
      "target_keywords": [
        "how to protect yourself online",
        "online security checklist",
        "internet safety tips 2026",
        "how to stay safe online",
        "digital security guide",
        "online privacy tips"
      ],
      "affiliate_links": [
        {
          "product": "NordVPN",
          "url": "https://go.nordvpn.net/aff_c?offer_id=612&aff_id=141337&url_id=14830",
          "placement": "vpn-section"
        },
        {
          "product": "NordPass",
          "url": "https://go.nordvpn.net/aff_c?offer_id=488&aff_id=141337",
          "placement": "password-section"
        },
        {
          "product": "Bitdefender",
          "url": "https://www.awin1.com/awclick.php?mid=11660&id=2776410",
          "placement": "antivirus-section"
        },
        {
          "product": "Surfshark",
          "url": "https://www.awin1.com/awclick.php?mid=36608&id=2776410",
          "placement": "vpn-budget-alt"
        }
      ],
      "word_count_target": 5000,
      "priority": 1
    },
    {
      "slug": "best-vpn-for-travel-2026",
      "title": "Best VPN for Travel in 2026: Stay Secure on Public Wi-Fi Worldwide",
      "description": "Targets travelers concerned about public Wi-Fi security, hotel networks, and accessing content abroad. Covers server coverage in key travel destinations, ease of use, multi-device support, and obfuscation features for restrictive countries like China and UAE. High commercial intent from a demographic willing to pay for security.",
      "category": "vpn",
      "content_type": "best-of-list",
      "target_keywords": [
        "best VPN for travel",
        "VPN for public Wi-Fi",
        "best VPN for traveling abroad",
        "VPN for hotel Wi-Fi",
        "best VPN for China 2026",
        "travel VPN"
      ],
      "affiliate_links": [
        {
          "product": "NordVPN",
          "url": "https://go.nordvpn.net/aff_c?offer_id=612&aff_id=141337&url_id=14830",
          "placement": "top-pick"
        },
        {
          "product": "Surfshark",
          "url": "https://www.awin1.com/awclick.php?mid=36608&id=2776410",
          "placement": "unlimited-devices-pick"
        }
      ],
      "word_count_target": 3500,
      "priority": 2
    },
    {
      "slug": "nordpass-review-2026",
      "title": "NordPass Review 2026: Simple Password Manager from the Makers of NordVPN",
      "description": "Dedicated review of NordPass, a direct affiliate partner with its own offer ID. Covers the password manager's zero-knowledge architecture, passkey support, data breach scanner, password health checker, and cross-platform apps. Compares against 1Password and Bitwarden to capture comparison traffic as well.",
      "category": "password-managers",
      "content_type": "product-review",
      "target_keywords": [
        "NordPass review 2026",
        "NordPass review",
        "is NordPass good",
        "NordPass vs 1Password",
        "NordPass password manager",
        "NordPass free vs premium"
      ],
      "affiliate_links": [
        {
          "product": "NordPass",
          "url": "https://go.nordvpn.net/aff_c?offer_id=488&aff_id=141337",
          "placement": "primary-cta"
        },
        {
          "product": "NordVPN",
          "url": "https://go.nordvpn.net/aff_c?offer_id=612&aff_id=141337&url_id=14830",
          "placement": "bundle-recommendation"
        }
      ],
      "word_count_target": 3500,
      "priority": 1
    },
    {
      "slug": "best-parental-control-software-2026",
      "title": "Best Parental Control Software in 2026: Keep Your Kids Safe Online",
      "description": "Targets parents searching for child safety solutions, a segment with high emotional urgency and willingness to pay. Covers content filtering, screen time management, location tracking, social media monitoring, and app blocking. Many of the site's antivirus affiliates (Bitdefender, Kaspersky, ESET) include parental controls in premium tiers, creating strong upsell opportunities.",
      "category": "privacy",
      "content_type": "best-of-list",
      "target_keywords": [
        "best parental control software 2026",
        "parental controls for internet",
        "best parental control app",
        "how to monitor kids online",
        "internet safety for kids",
        "best child safety software"
      ],
      "affiliate_links": [
        {
          "product": "Bitdefender",
          "url": "https://www.awin1.com/awclick.php?mid=11660&id=2776410",
          "placement": "best-bundled"
        },
        {
          "product": "Kaspersky",
          "url": "https://www.awin1.com/awclick.php?mid=19487&id=2776410",
          "placement": "safe-kids-pick"
        },
        {
          "product": "ESET",
          "url": "https://www.awin1.com/awclick.php?mid=18785&id=2776410",
          "placement": "parental-control-module"
        }
      ],
      "word_count_target": 4000,
      "priority": 2
    },
    {
      "slug": "how-to-set-up-two-factor-authentication-2026",
      "title": "How to Set Up Two-Factor Authentication (2FA) on Every Account",
      "description": "Extremely high search volume informational guide with evergreen relevance. Walks readers through enabling 2FA on Google, Apple, Microsoft, social media, banking, and crypto accounts. Naturally recommends password managers with built-in TOTP authenticators (NordPass, 1Password) as the best way to manage 2FA codes, driving affiliate conversions from an educational entry point.",
      "category": "privacy",
      "content_type": "how-to-guide",
      "target_keywords": [
        "how to set up two-factor authentication",
        "how to enable 2FA",
        "two-factor authentication guide",
        "best 2FA app 2026",
        "2FA setup guide",
        "how to set up authenticator app"
      ],
      "affiliate_links": [
        {
          "product": "NordPass",
          "url": "https://go.nordvpn.net/aff_c?offer_id=488&aff_id=141337",
          "placement": "authenticator-recommendation"
        },
        {
          "product": "NordVPN",
          "url": "https://go.nordvpn.net/aff_c?offer_id=612&aff_id=141337&url_id=14830",
          "placement": "account-security-bundle"
        }
      ],
      "word_count_target": 3000,
      "priority": 2
    },
    {
      "slug": "kaspersky-vs-bitdefender-2026",
      "title": "Kaspersky vs Bitdefender 2026: Which Antivirus Wins?",
      "description": "Head-to-head comparison of two major AWIN affiliate partners. One of the most searched antivirus comparison queries. Covers malware detection rates, system performance impact, feature sets, pricing, independent lab results, and platform support. Both options are site affiliate partners so every conversion is monetized regardless of which product the reader chooses.",
      "category": "antivirus",
      "content_type": "comparison",
      "target_keywords": [
        "Kaspersky vs Bitdefender",
        "Bitdefender vs Kaspersky",
        "Kaspersky vs Bitdefender 2026",
        "Kaspersky or Bitdefender",
        "best antivirus Kaspersky or Bitdefender",
        "Kaspersky vs Bitdefender comparison"
      ],
      "affiliate_links": [
        {
          "product": "Bitdefender",
          "url": "https://www.awin1.com/awclick.php?mid=11660&id=2776410",
          "placement": "option-a"
        },
        {
          "product": "Kaspersky",
          "url": "https://www.awin1.com/awclick.php?mid=19487&id=2776410",
          "placement": "option-b"
        }
      ],
      "word_count_target": 3500,
      "priority": 1
    },
    {
      "slug": "what-is-a-vpn-and-do-you-need-one-2026",
      "title": "What Is a VPN and Do You Actually Need One in 2026?",
      "description": "Top-of-funnel educational content targeting the massive informational query 'what is a VPN'. Explains VPN technology in plain language, covers legitimate use cases (privacy, public Wi-Fi, streaming, remote work), addresses common myths, and guides readers toward the site's review and comparison content. Captures early-stage buyers who then convert through internal linking to product pages.",
      "category": "vpn",
      "content_type": "how-to-guide",
      "target_keywords": [
        "what is a VPN",
        "do I need a VPN",
        "what does a VPN do",
        "VPN explained",
        "should I use a VPN",
        "are VPNs worth it 2026"
      ],
      "affiliate_links": [
        {
          "product": "NordVPN",
          "url": "https://go.nordvpn.net/aff_c?offer_id=612&aff_id=141337&url_id=14830",
          "placement": "recommended-vpn"
        },
        {
          "product": "Surfshark",
          "url": "https://www.awin1.com/awclick.php?mid=36608&id=2776410",
          "placement": "budget-option"
        }
      ],
      "word_count_target": 3000,
      "priority": 2
    },
    {
      "slug": "best-antivirus-for-android-2026",
      "title": "Best Antivirus for Android in 2026: Top Mobile Security Apps",
      "description": "Targets the high-volume mobile security segment. Android has over 3 billion active devices and is the primary malware target in the mobile space. Covers real-time scanning, app permission auditing, anti-theft features, Wi-Fi security scanning, and SMS phishing protection. The existing site covers Mac antivirus but has no Android-specific content, leaving a major gap.",
      "category": "antivirus",
      "content_type": "best-of-list",
      "target_keywords": [
        "best antivirus for Android 2026",
        "best Android antivirus app",
        "do I need antivirus on Android",
        "Android security app",
        "best mobile antivirus 2026",
        "Android malware protection"
      ],
      "affiliate_links": [
        {
          "product": "Bitdefender",
          "url": "https://www.awin1.com/awclick.php?mid=11660&id=2776410",
          "placement": "top-pick"
        },
        {
          "product": "Kaspersky",
          "url": "https://www.awin1.com/awclick.php?mid=19487&id=2776410",
          "placement": "runner-up"
        },
        {
          "product": "ESET",
          "url": "https://www.awin1.com/awclick.php?mid=18785&id=2776410",
          "placement": "lightweight-pick"
        },
        {
          "product": "Surfshark Antivirus",
          "url": "https://www.awin1.com/awclick.php?mid=36608&id=2776410",
          "placement": "budget-pick"
        },
        {
          "product": "NordVPN",
          "url": "https://go.nordvpn.net/aff_c?offer_id=612&aff_id=141337&url_id=14830",
          "placement": "vpn-companion"
        }
      ],
      "word_count_target": 3500,
      "priority": 1
    },
    {
      "slug": "how-to-check-if-your-data-has-been-leaked-2026",
      "title": "How to Check If Your Personal Data Has Been Leaked (And What to Do Next)",
      "description": "Capitalizes on anxiety around data breaches, which are constantly in the news. Covers breach-checking tools like HaveIBeenPwned, dark web monitoring services, credit freeze procedures, and actionable steps after discovering a leak. Naturally funnels readers toward password managers (to change compromised passwords), VPNs (to prevent future leaks), and identity theft protection services.",
      "category": "privacy",
      "content_type": "how-to-guide",
      "target_keywords": [
        "how to check if my data has been leaked",
        "have I been hacked",
        "data breach check",
        "has my email been compromised",
        "what to do after data breach",
        "dark web monitoring"
      ],
      "affiliate_links": [
        {
          "product": "NordPass",
          "url": "https://go.nordvpn.net/aff_c?offer_id=488&aff_id=141337",
          "placement": "data-breach-scanner"
        },
        {
          "product": "NordVPN",
          "url": "https://go.nordvpn.net/aff_c?offer_id=612&aff_id=141337&url_id=14830",
          "placement": "threat-protection"
        },
        {
          "product": "Bitdefender",
          "url": "https://www.awin1.com/awclick.php?mid=11660&id=2776410",
          "placement": "digital-identity-protection"
        },
        {
          "product": "Surfshark",
          "url": "https://www.awin1.com/awclick.php?mid=36608&id=2776410",
          "placement": "surfshark-alert"
        }
      ],
      "word_count_target": 3000,
      "priority": 2
    },
    {
      "slug": "best-vpn-for-gaming-2026",
      "title": "Best VPN for Gaming in 2026: Lowest Ping, No Lag",
      "description": "Targets the gaming audience, a large and highly engaged demographic. Covers latency benchmarks across popular game servers, DDoS protection, ISP throttling bypass, accessing geo-locked game servers, and reducing packet loss. Gamers are tech-savvy buyers who research thoroughly before purchasing, making them ideal affiliate conversion targets.",
      "category": "vpn",
      "content_type": "best-of-list",
      "target_keywords": [
        "best VPN for gaming 2026",
        "gaming VPN",
        "lowest latency VPN",
        "VPN for online gaming",
        "best VPN for low ping",
        "VPN DDoS protection gaming"
      ],
      "affiliate_links": [
        {
          "product": "NordVPN",
          "url": "https://go.nordvpn.net/aff_c?offer_id=612&aff_id=141337&url_id=14830",
          "placement": "top-pick"
        },
        {
          "product": "Surfshark",
          "url": "https://www.awin1.com/awclick.php?mid=36608&id=2776410",
          "placement": "value-pick"
        }
      ],
      "word_count_target": 3500,
      "priority": 2
    }
  ]
}
